{
    "boss": {
        "version": "1.0.0"
    },
    "application": {
        "bundleId": "io.bithead.lean",
        "name": "Lean",
        "version": "1.0.0",
        "system": false,
        "icon": "icon.svg",
        "main": "Application",
        "author": "Eric Chamberlain",
        "copyright": "2026 Bithead LLC. All rights reserved.",
        "secure": true,
        "quitAutomatically": false
    },
    "controllers": {
        "About": {
            "modal": true
        },
        "ClearHold": {
            "modal": true
        },
        "CreateFactoryModel": {
            "modal": true
        },
        "CreateLineModel": {
            "modal": true
        },
        "CreateOperation": {
            "modal": true
        },
        "CreateSupply": {
            "modal": true
        },
        "CreateSupplyField": {
            "modal": true
        },
        "CreateWorkUnit": {},
        "Factory": {},
        "Factories": {
            "singleton": true
        },
        "FactoryFloor": {
            "singleton": true,
            "godot": {
                "title": "Factory floor",
                "main": "FactoryFloor.html",
                "project": {
                    "name": "FactoryFloor",
                    "path": "~/source/io.bithead.lean/godot"
                }
            }
        },
        "Home": {
            "singleton": true
        },
        "WorkUnit": {},
        "WorkUnits": {},
        "OutputWorkUnits": {},
        "Workspace": { },
        "Company": {},
        "IntakeQueue": {},
        "Inventory": {},
        "Line": {},
        "Operator": {},
        "Station": {},
        "StationNotificationTrigger": {},
        "Operation": {},
        "Supply": {},
        "SupplyField": {},
        "SupplyFieldOption": {},
        "WaiveOperation": {
            "modal": true
        }
    }
}
